jamf/.DS_Store
jamf/__init__.py
jamf-0.1.0.dist-info/LICENSE
jamf-0.1.0.dist-info/WHEEL
jamf-0.1.0.dist-info/METADATA
jamf-0.1.0.dist-info/RECORD
